tdtgtd/__init__.py
tdtgtd/rst2odt.py
tdtgtd/tdtbackup.py
tdtgtd/tdtcleanup.py
tdtgtd/tdtlist.py
tdtgtd/tdtproj.py
tdtgtd/utils.py
todo.txt_gtd-0.2.dist-info/LICENSE
todo.txt_gtd-0.2.dist-info/METADATA
todo.txt_gtd-0.2.dist-info/WHEEL
todo.txt_gtd-0.2.dist-info/entry_points.txt
todo.txt_gtd-0.2.dist-info/top_level.txt
todo.txt_gtd-0.2.dist-info/RECORD
