Metadata-Version: 2.1
Name: todo.txt-gtd
Version: 0.2
Summary: Todo.txt support scripts for GTD.
Home-page: https://github.com/davesteele/todo.txt-gtd
Author: David Steele
Author-email: dsteele@gmail.com
License: GPL 2.0
Platform: UNKNOWN
Classifier: Development Status :: 5 - Production/Stable
Classifier: Intended Audience :: End Users/Desktop
Classifier: License :: OSI Approved :: GNU General Public License v2 or later (GPLv2+)
Classifier: Natural Language :: English
Classifier: Operating System :: POSIX :: Linux
Classifier: Operating System :: MacOS
Classifier: Operating System :: Microsoft :: Windows
Classifier: Programming Language :: Python :: 3 :: Only
Classifier: Topic :: Other/Nonlisted Topic
